infuzu/__init__.py
infuzu/api_client.py
infuzu/errors.py
infuzu-0.1.18.dist-info/METADATA
infuzu-0.1.18.dist-info/WHEEL
infuzu-0.1.18.dist-info/licenses/LICENSE
infuzu-0.1.18.dist-info/RECORD
