Metadata-Version: 2.4
Name: infuzu
Version: 0.1.18
Summary: Python SDK for Infuzu API
Project-URL: Homepage, https://github.com/Infuzu/infuzu-python
Project-URL: Repository, https://infuzu.com#api
Project-URL: Documentation, https://docs.infuzu.com
Author-email: Infuzu <support@infuuz.com>
License-Expression: Apache-2.0
License-File: LICENSE
Keywords: ai,api,artificial intelligence,chat,ims,infuzu,intelligent model selection,python,sdk
Classifier: Intended Audience :: Developers
Classifier: License :: OSI Approved :: Apache Software License
Classifier: Operating System :: MacOS
Classifier: Operating System :: Microsoft :: Windows
Classifier: Operating System :: OS Independent
Classifier: Operating System :: POSIX
Classifier: Operating System :: POSIX :: Linux
Classifier: Programming Language :: Python :: 3.8
Classifier: Programming Language :: Python :: 3.9
Classifier: Programming Language :: Python :: 3.10
Classifier: Programming Language :: Python :: 3.11
Classifier: Programming Language :: Python :: 3.12
Classifier: Topic :: Software Development :: Libraries :: Python Modules
Classifier: Typing :: Typed
Requires-Python: >=3.8
Requires-Dist: httpx<1,>=0.23.0
Requires-Dist: pydantic<3,>=2.0
Provides-Extra: test
Requires-Dist: pytest-cov>=4.0.0; extra == 'test'
Requires-Dist: pytest>=7.0.0; extra == 'test'
